Metadata-Version: 2.1
Name: autolinux
Version: 0.0.2
Summary: Linux automation classes
Home-page: https://github.com/ilkermanap/autolinux
Author: Ilker Manap
Author-email: ilkermanap@gmail.com
License: UNKNOWN
Platform: UNKNOWN
Classifier: Programming Language :: Python :: 3
Classifier: License :: OSI Approved :: GNU General Public License v3 (GPLv3)
Classifier: Operating System :: OS Independent
